django_viewflow-2.2.13.dist-info/licenses/LICENSE
viewflow/__init__.py
viewflow/apps.py
viewflow/conf.py
viewflow/fields.py
viewflow/jsonstore.py
viewflow/middleware.py
viewflow/this_object.py
viewflow/utils.py
viewflow/contrib/__init__.py
viewflow/contrib/auth.py
viewflow/contrib/admin/__init__.py
viewflow/contrib/admin/apps.py
viewflow/contrib/plotly/__init__.py
viewflow/contrib/plotly/material.py
viewflow/contrib/plotly/views.py
viewflow/contrib/plotly/viewset.py
viewflow/forms/__init__.py
viewflow/forms/renderers.py
viewflow/fsm/__init__.py
viewflow/fsm/admin.py
viewflow/fsm/base.py
viewflow/fsm/chart.py
viewflow/fsm/typing.py
viewflow/fsm/views.py
viewflow/fsm/viewset.py
viewflow/locale/de/LC_MESSAGES/django.mo
viewflow/locale/de/LC_MESSAGES/django.po
viewflow/locale/es/LC_MESSAGES/django.mo
viewflow/locale/es/LC_MESSAGES/django.po
viewflow/locale/fr/LC_MESSAGES/django.mo
viewflow/locale/fr/LC_MESSAGES/django.po
viewflow/locale/it/LC_MESSAGES/django.mo
viewflow/locale/it/LC_MESSAGES/django.po
viewflow/locale/ja/LC_MESSAGES/django.mo
viewflow/locale/ja/LC_MESSAGES/django.po
viewflow/locale/kk/LC_MESSAGES/django.mo
viewflow/locale/kk/LC_MESSAGES/django.po
viewflow/locale/ko/LC_MESSAGES/django.mo
viewflow/locale/ko/LC_MESSAGES/django.po
viewflow/locale/pt/LC_MESSAGES/django.mo
viewflow/locale/pt/LC_MESSAGES/django.po
viewflow/locale/ru/LC_MESSAGES/django.mo
viewflow/locale/ru/LC_MESSAGES/django.po
viewflow/locale/sr/LC_MESSAGES/django.mo
viewflow/locale/sr/LC_MESSAGES/django.po
viewflow/locale/zh_Hans/LC_MESSAGES/django.mo
viewflow/locale/zh_Hans/LC_MESSAGES/django.po
viewflow/management/__init__.py
viewflow/management/commands/__init__.py
viewflow/management/commands/flowexport.py
viewflow/static/viewflow/css/perfect-scrollbar.css
viewflow/static/viewflow/css/trix.css
viewflow/static/viewflow/css/viewflow.min.css
viewflow/static/viewflow/css/vis-network.min.css
viewflow/static/viewflow/fonts/material-icons/material-icons-outlined.woff
viewflow/static/viewflow/fonts/material-icons/material-icons-outlined.woff2
django_viewflow-2.2.13.dist-info/METADATA
django_viewflow-2.2.13.dist-info/WHEEL
django_viewflow-2.2.13.dist-info/top_level.txt
django_viewflow-2.2.13.dist-info/RECORD
